pgnotify_u/__init__.py
pgnotify_u/notify.py
pgnotify_u-0.2.dist-info/LICENSE
pgnotify_u-0.2.dist-info/WHEEL
pgnotify_u-0.2.dist-info/METADATA
pgnotify_u-0.2.dist-info/RECORD
