Metadata-Version: 2.1
Name: pgnotify-u
Version: 0.2
Summary: Easily LISTEN and NOTIFY to PostgreSQL notifications system
Home-page: https://github.com/glowlex/pgnotify
License: Unlicense
Author: glowlex
Author-email: glowlex@yandex.ru
Classifier: License :: Other/Proprietary License
Classifier: Programming Language :: Python :: 2
Classifier: Programming Language :: Python :: 2.7
Classifier: Programming Language :: Python :: 3
Classifier: Programming Language :: Python :: 3.4
Classifier: Programming Language :: Python :: 3.5
Classifier: Programming Language :: Python :: 3.6
Classifier: Programming Language :: Python :: 3.7
Classifier: Programming Language :: Python :: 3.8
Classifier: Programming Language :: Python :: 3.9
Requires-Dist: logx
Requires-Dist: psycopg2-binary
Requires-Dist: six
Project-URL: Repository, https://github.com/glowlex/pgnotify
